{
  "description": "",
  "supported_items": "#minecraft:enchantable/armor",
  "weight": 1,
  "max_level": 10,
  "min_cost": {
    "base": 0,
    "per_level_above_first": 0
  },
  "max_cost": {
    "base": 0,
    "per_level_above_first": 0
  },
  "anvil_cost": 0,
  "slots": [
    "any"
  ],
  "effects": {
    "minecraft:tick": [
      {
        "requirements": {
          "condition": "minecraft:entity_scores",
          "entity": "this",
          "scores": {
            "fizzy": 1
          }
        },
        "effect": {
          "type": "minecraft:all_of",
          "effects": [
            {
              "type": "minecraft:run_function",
              "function": "core:subweapons/fizzybomb/reset_score"
            },
            {
              "type": "minecraft:apply_impulse",
              "direction": [
                0,
                1.3,
                -0.5
              ],
              "coordinate_scale": [
                1,
                1,
                1
              ],
              "magnitude": {
                "type": "minecraft:linear",
                "base": 0.5,
                "per_level_above_first": 0.1
              }
            }
          ]
        }
      }
    ]
  }
}